epsonrc/__init__.py
epsonrc/commands.py
epsonrc-0.2.0.dist-info/licenses/LICENSE.txt
epsonrc-0.2.0.dist-info/METADATA
epsonrc-0.2.0.dist-info/WHEEL
epsonrc-0.2.0.dist-info/top_level.txt
epsonrc-0.2.0.dist-info/RECORD
