Metadata-Version: 2.4
Name: epsonrc
Version: 0.2.0
Summary: Python library for controlling industrial EPSON robots over TCP/IP
Author: David Rosales
Author-email: David Rosales <daparohe@gmail.com>
License: MIT
Project-URL: Homepage, https://github.com/daparohe/EPSONRC-Library
Project-URL: Repository, https://github.com/daparohe/EPSONRC-Library
Project-URL: Documentation, https://github.com/daparohe/EPSONRC-Library#readme
Project-URL: Bug Tracker, https://github.com/daparohe/EPSONRC-Library/issues
Keywords: robot,industrial,automation,epson,tcp,control,robotics
Classifier: Development Status :: 4 - Beta
Classifier: Intended Audience :: Developers
Classifier: Intended Audience :: Manufacturing
Classifier: License :: OSI Approved :: MIT License
Classifier: Programming Language :: Python :: 3
Classifier: Programming Language :: Python :: 3.7
Classifier: Programming Language :: Python :: 3.8
Classifier: Programming Language :: Python :: 3.9
Classifier: Programming Language :: Python :: 3.10
Classifier: Programming Language :: Python :: 3.11
Classifier: Programming Language :: Python :: 3.12
Classifier: Topic :: Software Development :: Libraries :: Python Modules
Classifier: Topic :: System :: Hardware
Requires-Python: >=3.7
License-File: LICENSE.txt
Dynamic: author
Dynamic: license-file
Dynamic: requires-python
